Workbook
Name Slicer_Center_Type: #N/A
Name Slicer_Issue_Category: #N/A
Name Slicer_Issue_Severity: #N/A
Name Slicer_Region: #N/A
Name Slicer_Service_Type: #N/A

Sheet Raw_Data
A1: Job_ID | B1: Job_Date | C1: Region | D1: City | E1: Service_Center | F1: Center_Type | G1: Vehicle_Model | H1: Vehicle_Segment | I1: Service_Type | J1: Issue_Category | K1: Issue_Severity | L1: Parts_Availability | M1: TAT_Days | N1: SLA_TAT | O1: Rework_Flag | P1: Warranty_Claim | Q1: Service_Revenue | R1: Service_Cost | S1: Profit | T1: Customer_Satisfaction | U1: Revenue_at_Risk | V1: Warranty_claim_Num | W1: First_time_num | X1: Repeat_visit_num | Y1: count_of_job | Z1: SLA_Breached | AA1: Customer_satisfaction_bucket
A2: 20000 | B2: 45378 | C2: South | D2: Chennai | E2: SC_CHE_5 | F2: Authorized | G2: Macan | H2: SUV | I2: Paid | J2: Suspension | K2: High | L2: Available | M2: 25 | N2: 7 | O2: Yes | P2: Yes | Q2: 243818 | R2: 184097 | S2: =Table1[[#This Row],[Service_Revenue]]-Table1[[#This Row],[Service_Cost]] -> 59721 | T2: 1 | U2: =IF(AND(Table1[[#This Row],[Rework_Flag]]="Yes",Table1[[#This Row],[Warranty_Claim]]="No"),Table1[[#This Row],[Service_Revenue]],0) -> 0 | V2: =IF(Table1[[#This Row],[Warranty_Claim]]="Yes",1,0) -> 1 | W2: =IF(Table1[[#This Row],[Rework_Flag]]="No",1,0) -> 0 | X2: =IF(Table1[[#This Row],[Rework_Flag]]="Yes",1,0) -> 1 | Y2: 1 | Z2: =IF(Table1[[#This Row],[TAT_Days]]>Table1[[#This Row],[SLA_TAT]],"Yes","No") -> Yes | AA2: {=_xlfn.IFS(Table1[[#This Row],[Customer_Satisfaction]]<=2,"Poor",Table1[[#This Row],[Customer_Satisfaction]]=3,"Neutral",Table1[[#This Row],[Customer_Satisfaction]]=4,"Good",Table1[[#This Row],[Customer_Satisfaction]]=5,"Good")} -> Poor
A3: 20001 | B3: 45355 | C3: East | D3: Patna | E3: SC_PAT_3 | F3: Authorized | G3: Veyron | H3: Hypercar | I3: Paid | J3: Engine | K3: High | L3: Available | M3: 12 | N3: 7 | O3: Yes | P3: No | Q3: 190119 | R3: 124471 | S3: =Table1[[#This Row],[Service_Revenue]]-Table1[[#This Row],[Service_Cost]] -> 65648 | T3: 2 | U3: =IF(AND(Table1[[#This Row],[Rework_Flag]]="Yes",Table1[[#This Row],[Warranty_Claim]]="No"),Table1[[#This Row],[Service_Revenue]],0) -> 190119 | V3: =IF(Table1[[#This Row],[Warranty_Claim]]="Yes",1,0) -> 0 | W3: =IF(Table1[[#This Row],[Rework_Flag]]="No",1,0) -> 0 | X3: =IF(Table1[[#This Row],[Rework_Flag]]="Yes",1,0) -> 1 | Y3: 1 | Z3: =IF(Table1[[#This Row],[TAT_Days]]>Table1[[#This Row],[SLA_TAT]],"Yes","No") -> Yes | AA3: {=_xlfn.IFS(Table1[[#This Row],[Customer_Satisfaction]]<=2,"Poor",Table1[[#This Row],[Customer_Satisfaction]]=3,"Neutral",Table1[[#This Row],[Customer_Satisfaction]]=4,"Good",Table1[[#This Row],[Customer_Satisfaction]]=5,"Good")} -> Poor
A4: 20002 | B4: 45332 | C4: North | D4: Noida | E4: SC_NOI_3 | F4: Flagship | G4: Taycan | H4: Sedan | I4: Paid | J4: Transmission | K4: Low | L4: Available | M4: 17 | N4: 7 | O4: Yes | P4: No | Q4: 314035 | R4: 232840 | S4: =Table1[[#This Row],[Service_Revenue]]-Table1[[#This Row],[Service_Cost]] -> 81195 | T4: 1 | U4: =IF(AND(Table1[[#This Row],[Rework_Flag]]="Yes",Table1[[#This Row],[Warranty_Claim]]="No"),Table1[[#This Row],[Service_Revenue]],0) -> 314035 | V4: =IF(Table1[[#This Row],[Warranty_Claim]]="Yes",1,0) -> 0 | W4: =IF(Table1[[#This Row],[Rework_Flag]]="No",1,0) -> 0 | X4: =IF(Table1[[#This Row],[Rework_Flag]]="Yes",1,0) -> 1 | Y4: 1 | Z4: =IF(Table1[[#This Row],[TAT_Days]]>Table1[[#This Row],[SLA_TAT]],"Yes","No") -> Yes | AA4: {=_xlfn.IFS(Table1[[#This Row],[Customer_Satisfaction]]<=2,"Poor",Table1[[#This Row],[Customer_Satisfaction]]=3,"Neutral",Table1[[#This Row],[Customer_Satisfaction]]=4,"Good",Table1[[#This Row],[Customer_Satisfaction]]=5,"Good")} -> Poor
A5: 20003 | B5: 45442 | C5: South | D5: Bengaluru | E5: SC_BEN_1 | F5: Flagship | G5: 911 | H5: Coupe | I5: Paid | J5: Suspension | K5: Low | L5: Delayed | M5: 12 | N5: 7 | O5: No | P5: No | Q5: 206050 | R5: 155487 | S5: =Table1[[#This Row],[Service_Revenue]]-Table1[[#This Row],[Service_Cost]] -> 50563 | T5: 3 | U5: =IF(AND(Table1[[#This Row],[Rework_Flag]]="Yes",Table1[[#This Row],[Warranty_Claim]]="No"),Table1[[#This Row],[Service_Revenue]],0) -> 0 | V5: =IF(Table1[[#This Row],[Warranty_Claim]]="Yes",1,0) -> 0 | W5: =IF(Table1[[#This Row],[Rework_Flag]]="No",1,0) -> 1 | X5: =IF(Table1[[#This Row],[Rework_Flag]]="Yes",1,0) -> 0 | Y5: 1 | Z5: =IF(Table1[[#This Row],[TAT_Days]]>Table1[[#This Row],[SLA_TAT]],"Yes","No") -> Yes | AA5: {=_xlfn.IFS(Table1[[#This Row],[Customer_Satisfaction]]<=2,"Poor",Table1[[#This Row],[Customer_Satisfaction]]=3,"Neutral",Table1[[#This Row],[Customer_Satisfaction]]=4,"Good",Table1[[#This Row],[Customer_Satisfaction]]=5,"Good")} -> Neutral
A6: 20004 | B6: 45441 | C6: West | D6: Mumbai | E6: SC_MUM_5 | F6: Dealer | G6: Panamera | H6: Sedan | I6: Warranty | J6: Transmission | K6: High | L6: Delayed | M6: 25 | N6: 7 | O6: Yes | P6: No | Q6: 148961 | R6: 122991 | S6: =Table1[[#This Row],[Service_Revenue]]-Table1[[#This Row],[Service_Cost]] -> 25970 | T6: 1 | U6: =IF(AND(Table1[[#This Row],[Rework_Flag]]="Yes",Table1[[#This Row],[Warranty_Claim]]="No"),Table1[[#This Row],[Service_Revenue]],0) -> 148961 | V6: =IF(Table1[[#This Row],[Warranty_Claim]]="Yes",1,0) -> 0 | W6: =IF(Table1[[#This Row],[Rework_Flag]]="No",1,0) -> 0 | X6: =IF(Table1[[#This Row],[Rework_Flag]]="Yes",1,0) -> 1 | Y6: 1 | Z6: =IF(Table1[[#This Row],[TAT_Days]]>Table1[[#This Row],[SLA_TAT]],"Yes","No") -> Yes | AA6: {=_xlfn.IFS(Table1[[#This Row],[Customer_Satisfaction]]<=2,"Poor",Table1[[#This Row],[Customer_Satisfaction]]=3,"Neutral",Table1[[#This Row],[Customer_Satisfaction]]=4,"Good",Table1[[#This Row],[Customer_Satisfaction]]=5,"Good")} -> Poor
A7: 20005 | B7: 45354 | C7: West | D7: Pune | E7: SC_PUN_1 | F7: Authorized | G7: Veyron | H7: Hypercar | I7: Paid | J7: Body | K7: Low | L7: Delayed | M7: 3 | N7: 7 | O7: Yes | P7: Yes | Q7: 101553 | R7: 75203 | S7: =Table1[[#This Row],[Service_Revenue]]-Table1[[#This Row],[Service_Cost]] -> 26350 | T7: 4 | U7: =IF(AND(Table1[[#This Row],[Rework_Flag]]="Yes",Table1[[#This Row],[Warranty_Claim]]="No"),Table1[[#This Row],[Service_Revenue]],0) -> 0 | V7: =IF(Table1[[#This Row],[Warranty_Claim]]="Yes",1,0) -> 1 | W7: =IF(Table1[[#This Row],[Rework_Flag]]="No",1,0) -> 0 | X7: =IF(Table1[[#This Row],[Rework_Flag]]="Yes",1,0) -> 1 | Y7: 1 | Z7: =IF(Table1[[#This Row],[TAT_Days]]>Table1[[#This Row],[SLA_TAT]],"Yes","No") -> No | AA7: {=_xlfn.IFS(Table1[[#This Row],[Customer_Satisfaction]]<=2,"Poor",Table1[[#This Row],[Customer_Satisfaction]]=3,"Neutral",Table1[[#This Row],[Customer_Satisfaction]]=4,"Good",Table1[[#This Row],[Customer_Satisfaction]]=5,"Good")} -> Good
A8: 20006 | B8: 45458 | C8: East | D8: Bhubaneswar | E8: SC_BHU_1 | F8: Flagship | G8: Macan | H8: SUV | I8: Warranty | J8: Suspension | K8: Medium | L8: Available | M8: 10 | N8: 7 | O8: Yes | P8: Yes | Q8: 314895 | R8: 223154 | S8: =Table1[[#This Row],[Service_Revenue]]-Table1[[#This Row],[Service_Cost]] -> 91741 | T8: 2 | U8: =IF(AND(Table1[[#This Row],[Rework_Flag]]="Yes",Table1[[#This Row],[Warranty_Claim]]="No"),Table1[[#This Row],[Service_Revenue]],0) -> 0 | V8: =IF(Table1[[#This Row],[Warranty_Claim]]="Yes",1,0) -> 1 | W8: =IF(Table1[[#This Row],[Rework_Flag]]="No",1,0) -> 0 | X8: =IF(Table1[[#This Row],[Rework_Flag]]="Yes",1,0) -> 1 | Y8: 1 | Z8: =IF(Table1[[#This Row],[TAT_Days]]>Table1[[#This Row],[SLA_TAT]],"Yes","No") -> Yes | AA8: {=_xlfn.IFS(Table1[[#This Row],[Customer_Satisfaction]]<=2,"Poor",Table1[[#This Row],[Customer_Satisfaction]]=3,"Neutral",Table1[[#This Row],[Customer_Satisfaction]]=4,"Good",Table1[[#This Row],[Customer_Satisfaction]]=5,"Good")} -> Poor
A9: 20007 | B9: 45397 | C9: East | D9: Patna | E9: SC_PAT_2 | F9: Dealer | G9: Cayenne | H9: SUV | I9: Paid | J9: Engine | K9: Medium | L9: Delayed | M9: 10 | N9: 7 | O9: Yes | P9: No | Q9: 521120 | R9: 399852 | S9: =Table1[[#This Row],[Service_Revenue]]-Table1[[#This Row],[Service_Cost]] -> 121268 | T9: 2 | U9: =IF(AND(Table1[[#This Row],[Rework_Flag]]="Yes",Table1[[#This Row],[Warranty_Claim]]="No"),Table1[[#This Row],[Service_Revenue]],0) -> 521120 | V9: =IF(Table1[[#This Row],[Warranty_Claim]]="Yes",1,0) -> 0 | W9: =IF(Table1[[#This Row],[Rework_Flag]]="No",1,0) -> 0 | X9: =IF(Table1[[#This Row],[Rework_Flag]]="Yes",1,0) -> 1 | Y9: 1 | Z9: =IF(Table1[[#This Row],[TAT_Days]]>Table1[[#This Row],[SLA_TAT]],"Yes","No") -> Yes | AA9: {=_xlfn.IFS(Table1[[#This Row],[Customer_Satisfaction]]<=2,"Poor",Table1[[#This Row],[Customer_Satisfaction]]=3,"Neutral",Table1[[#This Row],[Customer_Satisfaction]]=4,"Good",Table1[[#This Row],[Customer_Satisfaction]]=5,"Good")} -> Poor
A10: 20008 | B10: 45365 | C10: North | D10: Delhi | E10: SC_DEL_4 | F10: Authorized | G10: Veyron | H10: Hypercar | I10: Paid | J10: Transmission | K10: High | L10: Delayed | M10: 3 | N10: 7 | O10: No | P10: No | Q10: 510335 | R10: 407767 | S10: =Table1[[#This Row],[Service_Revenue]]-Table1[[#This Row],[Service_Cost]] -> 102568 | T10: 5 | U10: =IF(AND(Table1[[#This Row],[Rework_Flag]]="Yes",Table1[[#This Row],[Warranty_Claim]]="No"),Table1[[#This Row],[Service_Revenue]],0) -> 0 | V10: =IF(Table1[[#This Row],[Warranty_Claim]]="Yes",1,0) -> 0 | W10: =IF(Table1[[#This Row],[Rework_Flag]]="No",1,0) -> 1 | X10: =IF(Table1[[#This Row],[Rework_Flag]]="Yes",1,0) -> 0 | Y10: 1 | Z10: =IF(Table1[[#This Row],[TAT_Days]]>Table1[[#This Row],[SLA_TAT]],"Yes","No") -> No | AA10: {=_xlfn.IFS(Table1[[#This Row],[Customer_Satisfaction]]<=2,"Poor",Table1[[#This Row],[Customer_Satisfaction]]=3,"Neutral",Table1[[#This Row],[Customer_Satisfaction]]=4,"Good",Table1[[#This Row],[Customer_Satisfaction]]=5,"Good")} -> Good
A11: 20009 | B11: 45446 | C11: East | D11: Bhubaneswar | E11: SC_BHU_5 | F11: Flagship | G11: Panamera | H11: Sedan | I11: Warranty | J11: Electronics | K11: High | L11: Delayed | M11: 3 | N11: 7 | O11: No | P11: Yes | Q11: 433317 | R11: 273962 | S11: =Table1[[#This Row],[Service_Revenue]]-Table1[[#This Row],[Service_Cost]] -> 159355 | T11: 5 | U11: =IF(AND(Table1[[#This Row],[Rework_Flag]]="Yes",Table1[[#This Row],[Warranty_Claim]]="No"),Table1[[#This Row],[Service_Revenue]],0) -> 0 | V11: =IF(Table1[[#This Row],[Warranty_Claim]]="Yes",1,0) -> 1 | W11: =IF(Table1[[#This Row],[Rework_Flag]]="No",1,0) -> 1 | X11: =IF(Table1[[#This Row],[Rework_Flag]]="Yes",1,0) -> 0 | Y11: 1 | Z11: =IF(Table1[[#This Row],[TAT_Days]]>Table1[[#This Row],[SLA_TAT]],"Yes","No") -> No | AA11: {=_xlfn.IFS(Table1[[#This Row],[Customer_Satisfaction]]<=2,"Poor",Table1[[#This Row],[Customer_Satisfaction]]=3,"Neutral",Table1[[#This Row],[Customer_Satisfaction]]=4,"Good",Table1[[#This Row],[Customer_Satisfaction]]=5,"Good")} -> Good
A12: 20010 | B12: 45293 | C12: West | D12: Pune | E12: SC_PUN_2 | F12: Flagship | G12: Macan | H12: SUV | I12: Paid | J12: Body | K12: High | L12: Delayed | M12: 11 | N12: 7 | O12: Yes | P12: No | Q12: 470727 | R12: 349785 | S12: =Table1[[#This Row],[Service_Revenue]]-Table1[[#This Row],[Service_Cost]] -> 120942 | T12: 2 | U12: =IF(AND(Table1[[#This Row],[Rework_Flag]]="Yes",Table1[[#This Row],[Warranty_Claim]]="No"),Table1[[#This Row],[Service_Revenue]],0) -> 470727 | V12: =IF(Table1[[#This Row],[Warranty_Claim]]="Yes",1,0) -> 0 | W12: =IF(Table1[[#This Row],[Rework_Flag]]="No",1,0) -> 0 | X12: =IF(Table1[[#This Row],[Rework_Flag]]="Yes",1,0) -> 1 | Y12: 1 | Z12: =IF(Table1[[#This Row],[TAT_Days]]>Table1[[#This Row],[SLA_TAT]],"Yes","No") -> Yes | AA12: {=_xlfn.IFS(Table1[[#This Row],[Customer_Satisfaction]]<=2,"Poor",Table1[[#This Row],[Customer_Satisfaction]]=3,"Neutral",Table1[[#This Row],[Customer_Satisfaction]]=4,"Good",Table1[[#This Row],[Customer_Satisfaction]]=5,"Good")} -> Poor
A13: 20011 | B13: 45427 | C13: East | D13: Bhubaneswar | E13: SC_BHU_2 | F13: Authorized | G13: Macan | H13: SUV | I13: Warranty | J13: Engine | K13: High | L13: Delayed | M13: 22 | N13: 7 | O13: Yes | P13: Yes | Q13: 168313 | R13: 142958 | S13: =Table1[[#This Row],[Service_Revenue]]-Table1[[#This Row],[Service_Cost]] -> 25355 | T13: 1 | U13: =IF(AND(Table1[[#This Row],[Rework_Flag]]="Yes",Table1[[#This Row],[Warranty_Claim]]="No"),Table1[[#This Row],[Service_Revenue]],0) -> 0 | V13: =IF(Table1[[#This Row],[Warranty_Claim]]="Yes",1,0) -> 1 | W13: =IF(Table1[[#This Row],[Rework_Flag]]="No",1,0) -> 0 | X13: =IF(Table1[[#This Row],[Rework_Flag]]="Yes",1,0) -> 1 | Y13: 1 | Z13: =IF(Table1[[#This Row],[TAT_Days]]>Table1[[#This Row],[SLA_TAT]],"Yes","No") -> Yes | AA13: {=_xlfn.IFS(Table1[[#This Row],[Customer_Satisfaction]]<=2,"Poor",Table1[[#This Row],[Customer_Satisfaction]]=3,"Neutral",Table1[[#This Row],[Customer_Satisfaction]]=4,"Good",Table1[[#This Row],[Customer_Satisfaction]]=5,"Good")} -> Poor
... A3001: 22999 | B3001: 45380 | C3001: West | D3001: Ahmedabad | E3001: SC_AHM_4 | F3001: Authorized | G3001: Taycan | H3001: Sedan | I3001: Warranty | J3001: Engine | K3001: High | L3001: Delayed | M3001: 7 | N3001: 7 | O3001: No | P3001: No | Q3001: 231498 | R3001: 136147 | S3001: =Table1[[#This Row],[Service_Revenue]]-Table1[[#This Row],[Service_Cost]] -> 95351 | T3001: 4 | U3001: =IF(AND(Table1[[#This Row],[Rework_Flag]]="Yes",Table1[[#This Row],[Warranty_Claim]]="No"),Table1[[#This Row],[Service_Revenue]],0) -> 0 | V3001: =IF(Table1[[#This Row],[Warranty_Claim]]="Yes",1,0) -> 0 | W3001: =IF(Table1[[#This Row],[Rework_Flag]]="No",1,0) -> 1 | X3001: =IF(Table1[[#This Row],[Rework_Flag]]="Yes",1,0) -> 0 | Y3001: 1 | Z3001: =IF(Table1[[#This Row],[TAT_Days]]>Table1[[#This Row],[SLA_TAT]],"Yes","No") -> No | AA3001: {=_xlfn.IFS(Table1[[#This Row],[Customer_Satisfaction]]<=2,"Poor",Table1[[#This Row],[Customer_Satisfaction]]=3,"Neutral",Table1[[#This Row],[Customer_Satisfaction]]=4,"Good",Table1[[#This Row],[Customer_Satisfaction]]=5,"Good")} -> Good

Sheet Project_Blueprint
A1: Luxury automotive service operations
A3: Context
A4: Automotive after sales Ops
A5: Revenue leakage and Ops performance analysis
A7: KPI
A8: Total Revenue
A9: Total Cost
A10: Profit
A11: Profit Margin %
A12: Revenue at Risk - rework and no warranty claim
A13: Warranty Claim Rate
A14: First Time Fix Rate
A15: Repeat Visit Rate
A17: Segment | D17: Slicers
A18: Region | D18: Region
A19: Vehicle_segment | D19: service_type
A20: Issue_category | D20: Parts_availabilty
A21: Parts_availability | D21: Warranty_claim
A22: Rework_flag
A24: Core Business Questions
A25: Where is company losing money
A26: How customer satisfaction is affected by TAT days
A27: What causes high TAT days
A28: How is Parts availabitity related to rework
A29: Does Rework flag reduce customer satisfaction
A31: Success after 30 days
A32: Revenue at risk Reduced
A33: Lower TAT days
A34: Lowered Rework Flag

Sheet Pivot_Calculations
A2: Sum of count_of_job | B2: Sum of Service_Revenue | C2: Sum of Service_Cost | D2: Sum of Profit | E2: Sum of Profit Margin % | F2: Sum of Revenue_at_Risk | G2: Sum of Warranty_claim_rate | H2: Sum of First_time_rate | I2: Sum of Repeat_visit_rate
A3: 3000 | B3: 1021143275 | C3: 687145899 | D3: 333997376 | E3: 0.3270818 | F3: 396046127 | G3: 0.35 | H3: 0.406 | I3: 0.594
A6: Region | B6: Sum of Service_Revenue
A7: East | B7: 274968321 | D7: Customer_satisfaction | E7: Average of TAT_Days | G7: Rework_flag | H7: Average of Customer_Satisfaction | I7: Average of TAT_Days | J7: Sum of Service_Cost | K7: Count of Job_ID
A8: North | B8: 240578013 | D8: 1 | E8: 20.516579 | G8: No | H8: 2.9761905 | I8: 12.311166 | J8: 276885931 | K8: 1218
A9: South | B9: 248647492 | D9: 2 | E9: 13.848875 | G9: Yes | H9: 1.8810325 | I9: 14.23064 | J9: 410259968 | K9: 1782
A10: West | B10: 256949449 | D10: 3 | E10: 9.1551402 | G10: Grand Total | H10: 2.3256667 | I10: 13.451333 | J10: 687145899 | K10: 3000
A11: Grand Total | B11: 1021143275 | D11: 4 | E11: 5.471173 | G11: rework causes high tat days, which causes high service cause and low customer satisfaction.Hence, profit reduced
D12: 5 | E12: 2.9793814 | G12: Revenue leakage is mainly due to Rework service cost
A13: Region | B13: Sum of Revenue_at_Risk | D13: Grand Total | E13: 13.451333 | J13: =GETPIVOTDATA("Sum of Service_Cost",$G$7,"Rework_flag",$G$9) -> 410259968
A14: East | B14: 101851567 | D14: High TAT days negatively affect customer satisfaction
A15: North | B15: 90931545 | H15: Sum of count_of_job | I15: Rework_flag
A16: South | B16: 105216238 | D16: Count of Parts_Availability | E16: Parts_availability | H16: Issue _severity | I16: No | J16: Yes | K16: Grand Total
A17: West | B17: 98046777 | D17: Rework_flag | E17: Available | F17: Delayed | G17: Grand Total | H17: High | I17: 161 | J17: 750 | K17: 911
A18: Grand Total | B18: 396046127 | D18: No | E18: 747 | F18: 471 | G18: 1218 | H18: Low | I18: 445 | J18: 457 | K18: 902
D19: Yes | E19: 1026 | F19: 756 | G19: 1782 | H19: Medium | I19: 612 | J19: 575 | K19: 1187
D20: Grand Total | E20: 1773 | F20: 1227 | G20: 3000 | H20: Grand Total | I20: 1218 | J20: 1782 | K20: 3000
D21: Rework is not affected mainly due to parts availability | H21: % of Rework jobs with severity high + medium | K21: =(J17+J19)/K20 -> 0.44166667
A22: Average of Customer_Satisfaction
A23: 2.3256667 | D23: Rework_flag | E23: Sum of Revenue_at_Risk | H23: Sum of Service_Cost | I23: Column Labels
D24: No | E24: 396046127 | H24: Rework_flag | I24: High | J24: Low | K24: Medium | L24: Grand Total
D25: Yes | E25: 0 | H25: No | I25: 37370509 | J25: 102393831 | K25: 137121591 | L25: 276885931
D26: Grand Total | E26: 396046127 | H26: Yes | I26: 170932393 | J26: 104692589 | K26: 134634986 | L26: 410259968
H27: Grand Total | I27: 208302902 | J27: 207086420 | K27: 271756577 | L27: 687145899
A28: Sum of Revenue_at_Risk | B28: Issue_severity | H28: Total service cost of High + Medium severity Rework job | K28: =(I26+K26)/L27 -> 0.44469068
A29: Region | B29: High | C29: Low | D29: Medium | E29: Grand Total
A30: East | B30: 40180901 | C30: 29917885 | D30: 31752781 | E30: 101851567
A31: North | B31: 41032859 | C31: 23210723 | D31: 26687963 | E31: 90931545
A32: South | B32: 40148092 | C32: 26881916 | D32: 38186230 | E32: 105216238
A33: West | B33: 38778375 | C33: 28175536 | D33: 31092866 | E33: 98046777
A34: Grand Total | B34: 160140227 | C34: 108186060 | D34: 127719840 | E34: 396046127
A36: Cust_satis_bucket | B36: Sum of Repeat_visit_rate | C36: Sum of count_of_job
A37: Good | B37: 0.276901 | C37: 697
A38: Neutral | B38: 0.55700935 | C38: 535
A39: Poor | B39: 0.73020362 | C39: 1768 | D39: =C39/C40 -> 0.58933333
A40: Grand Total | B40: 0.594 | C40: 3000

Sheet Dashboard
A1: Automotive After Sales Service Analysis-Revenue and Ops Performance Dashbboard
A5: Revenue | G5: Cost | M5: Profit | S5: Profit Margin % | Y5: Revenue at Risk | AE5: Service cost(Rework)
A6: =Pivot_Calculations!B3 -> 1021143275 | G6: =Pivot_Calculations!C3 -> 687145899 | M6: =Pivot_Calculations!D3 -> 333997376 | S6: =Pivot_Calculations!E3 -> 0.3270818 | Y6: =Pivot_Calculations!F3 -> 396046127 | AE6: =Pivot_Calculations!J13 -> 410259968
A10: No.of Jobs | G10: First Time Visit Rate | M10: Repeat Visit Rate | S10: Avg Customer Satisfaction(1-5) | Y10: Warranty Claim Rate | AE10: % Service Cost(Rework)
A11: =Pivot_Calculations!A3 -> 3000 | G11: =Pivot_Calculations!H3 -> 0.406 | M11: =Pivot_Calculations!I3 -> 0.594 | S11: =Pivot_Calculations!A23 -> 2.3256667 | Y11: =Pivot_Calculations!G3 -> 0.35 | AE11: =AE6/G6 -> 0.59704929
V15: Why Revenue is at Risk

Sheet Insights_Notes
A1: Insights | J1: Abbreviations
A2: 40% Revenue (41.02cr), is Leaking due to Service Cost(Rework). | J2: CSAT-Customer Satisfaction
A3: Due to High TAT days, 73% Customers have Poor Expericnce. | J3: FTF-First Time Fix
A4: 59% Jobs go to Rework causing High SLA breaches. | J4: TAT-Turnaround Time
A5: Parts availability affects TAT days more than Rework. | J5: SLA-Service Level Agreement
A6: Rework has negative effect on CSAT.
A8: Root Cause Hypotheses
A9: 40% of Revenue with just 35% Warranty claim, was spent on Service cost due to Rework.
A10: 1700+ customers rated satisfactory score 1-2. Hence, 73% customers had poor CSAT.
A11: 44.17% of Rework jobs with Issue Severity-High + Medium,Causes high TAT days.
A12: 57.57% Rework jobs already had Parts available. Hence, its related to TAT days more than Rework.
A13: Avg TAT for Rework vs FTF is 14.23 and 12.31,While avg CSAT for Rework vs FTF is 1.88 and 2.98. Hence, TAT Rise causes CSAT to Plumet
A15: Ceo Recommendations
A16: Action | Why | Impact | Piority | Owner
A17: Increase Warranty Claims | High Service Cost | Profit Increases | High | Finance Head
A18: Reduce SLA Breach | High service cost | Less Revenue at Risk | High | Ops Head
A19: Reduce Rework Jobs with Issue Severity High+ Medium(44.17% Jobs) | 44.47% Increase in Service cost | TAT days Reduction and CSAT Increases | High | Ops Head
... A23: Operations Performance Improved-Lower TAT days Increases CSAT. Hence, 73% Customers can have better Experience and 59% of Total Customers can come in FTF Category.
